natholi/__init__.py
natholi/national_holiday.py
natholi-0.1.1.dist-info/AUTHORS.rst
natholi-0.1.1.dist-info/LICENSE
natholi-0.1.1.dist-info/METADATA
natholi-0.1.1.dist-info/WHEEL
natholi-0.1.1.dist-info/top_level.txt
natholi-0.1.1.dist-info/RECORD
