Metadata-Version: 2.1
Name: natholi
Version: 0.1.1
Summary: A package allowing you to get national holidays for 200+ countries around the world.
Home-page: https://github.com/davidchapuis/natholi
Author: David Chapuis
Author-email: dah.chapuis@gmail.com
License: MIT license
Keywords: natholi
Classifier: Development Status :: 2 - Pre-Alpha
Classifier: Intended Audience :: Developers
Classifier: License :: OSI Approved :: MIT License
Classifier: Natural Language :: English
Classifier: Programming Language :: Python :: 3
Classifier: Programming Language :: Python :: 3.6
Classifier: Programming Language :: Python :: 3.7
Classifier: Programming Language :: Python :: 3.8
Requires-Python: >=3.6
License-File: LICENSE
License-File: AUTHORS.rst
